[
  {
    "DateUtc": "13/08/22",
    "HomeTeam": "Milan",
    "AwayTeam": "Udinese",
    "HomeTeamScore": 4,
    "AwayTeamScore": 2
  },
  {
    "DateUtc": "13/08/22",
    "HomeTeam": "Sampdoria",
    "AwayTeam": "Atalanta",
    "HomeTeamScore": 0,
    "AwayTeamScore": 2
  },
  {
    "DateUtc": "13/08/22",
    "HomeTeam": "Lecce",
    "AwayTeam": "Inter",
    "HomeTeamScore": 1,
    "AwayTeamScore": 2
  },
  {
    "DateUtc": "13/08/22",
    "HomeTeam": "Monza",
    "AwayTeam": "Torino",
    "HomeTeamScore": 1,
    "AwayTeamScore": 2
  },
  {
    "DateUtc": "14/08/22",
    "HomeTeam": "Fiorentina",
    "AwayTeam": "Cremonese",
    "HomeTeamScore": 3,
    "AwayTeamScore": 2
  },
  {
    "DateUtc": "14/08/22",
    "HomeTeam": "Lazio",
    "AwayTeam": "Bologna",
    "HomeTeamScore": 2,
    "AwayTeamScore": 1
  },
  {
    "DateUtc": "14/08/22",
    "HomeTeam": "Salernitana",
    "AwayTeam": "Roma",
    "HomeTeamScore": 0,
    "AwayTeamScore": 1
  },
  {
    "DateUtc": "14/08/22",
    "HomeTeam": "Spezia",
    "AwayTeam": "Empoli",
    "HomeTeamScore": 1,
    "AwayTeamScore": 0
  },
  {
    "DateUtc": "15/08/22",
    "HomeTeam": "Verona",
    "AwayTeam": "Napoli",
    "HomeTeamScore": 2,
    "AwayTeamScore": 5
  },
  {
    "DateUtc": "15/08/22",
    "HomeTeam": "Juventus",
    "AwayTeam": "Sassuolo",
    "HomeTeamScore": 3,
    "AwayTeamScore": 0
  },
  {
    "DateUtc": "20/08/22",
    "HomeTeam": "Torino",
    "AwayTeam": "Lazio",
    "HomeTeamScore": 0,
    "AwayTeamScore": 0
  },
  {
    "DateUtc": "20/08/22",
    "HomeTeam": "Udinese",
    "AwayTeam": "Salernitana",
    "HomeTeamScore": 0,
    "AwayTeamScore": 0
  },
  {
    "DateUtc": "20/08/22",
    "HomeTeam": "Inter",
    "AwayTeam": "Spezia",
    "HomeTeamScore": 3,
    "AwayTeamScore": 0
  },
  {
    "DateUtc": "20/08/22",
    "HomeTeam": "Sassuolo",
    "AwayTeam": "Lecce",
    "HomeTeamScore": 1,
    "AwayTeamScore": 0
  },
  {
    "DateUtc": "21/08/22",
    "HomeTeam": "Empoli",
    "AwayTeam": "Fiorentina",
    "HomeTeamScore": 0,
    "AwayTeamScore": 0
  },
  {
    "DateUtc": "21/08/22",
    "HomeTeam": "Napoli",
    "AwayTeam": "Monza",
    "HomeTeamScore": 4,
    "AwayTeamScore": 0
  },
  {
    "DateUtc": "21/08/22",
    "HomeTeam": "Atalanta",
    "AwayTeam": "Milan",
    "HomeTeamScore": 1,
    "AwayTeamScore": 1
  },
  {
    "DateUtc": "21/08/22",
    "HomeTeam": "Bologna",
    "AwayTeam": "Verona",
    "HomeTeamScore": 1,
    "AwayTeamScore": 1
  },
  {
    "DateUtc": "22/08/22",
    "HomeTeam": "Roma",
    "AwayTeam": "Cremonese",
    "HomeTeamScore": 1,
    "AwayTeamScore": 0
  },
  {
    "DateUtc": "22/08/22",
    "HomeTeam": "Sampdoria",
    "AwayTeam": "Juventus",
    "HomeTeamScore": 0,
    "AwayTeamScore": 0
  },
  {
    "DateUtc": "26/08/22",
    "HomeTeam": "Monza",
    "AwayTeam": "Udinese",
    "HomeTeamScore": 1,
    "AwayTeamScore": 2
  },
  {
    "DateUtc": "26/08/22",
    "HomeTeam": "Lazio",
    "AwayTeam": "Inter",
    "HomeTeamScore": 3,
    "AwayTeamScore": 1
  },
  {
    "DateUtc": "27/08/22",
    "HomeTeam": "Cremonese",
    "AwayTeam": "Torino",
    "HomeTeamScore": 1,
    "AwayTeamScore": 2
  },
  {
    "DateUtc": "27/08/22",
    "HomeTeam": "Juventus",
    "AwayTeam": "Roma",
    "HomeTeamScore": 1,
    "AwayTeamScore": 1
  },
  {
    "DateUtc": "27/08/22",
    "HomeTeam": "Milan",
    "AwayTeam": "Bologna",
    "HomeTeamScore": 2,
    "AwayTeamScore": 0
  },
  {
    "DateUtc": "27/08/22",
    "HomeTeam": "Spezia",
    "AwayTeam": "Sassuolo",
    "HomeTeamScore": 2,
    "AwayTeamScore": 2
  },
  {
    "DateUtc": "28/08/22",
    "HomeTeam": "Salernitana",
    "AwayTeam": "Sampdoria",
    "HomeTeamScore": 4,
    "AwayTeamScore": 0
  },
  {
    "DateUtc": "28/08/22",
    "HomeTeam": "Verona",
    "AwayTeam": "Atalanta",
    "HomeTeamScore": 0,
    "AwayTeamScore": 1
  },
  {
    "DateUtc": "28/08/22",
    "HomeTeam": "Fiorentina",
    "AwayTeam": "Napoli",
    "HomeTeamScore": 0,
    "AwayTeamScore": 0
  },
  {
    "DateUtc": "28/08/22",
    "HomeTeam": "Lecce",
    "AwayTeam": "Empoli",
    "HomeTeamScore": 1,
    "AwayTeamScore": 1
  },
  {
    "DateUtc": "30/08/22",
    "HomeTeam": "Sassuolo",
    "AwayTeam": "Milan",
    "HomeTeamScore": 0,
    "AwayTeamScore": 0
  },
  {
    "DateUtc": "30/08/22",
    "HomeTeam": "Inter",
    "AwayTeam": "Cremonese",
    "HomeTeamScore": 3,
    "AwayTeamScore": 1
  },
  {
    "DateUtc": "30/08/22",
    "HomeTeam": "Roma",
    "AwayTeam": "Monza",
    "HomeTeamScore": 3,
    "AwayTeamScore": 0
  },
  {
    "DateUtc": "31/08/22",
    "HomeTeam": "Empoli",
    "AwayTeam": "Verona",
    "HomeTeamScore": 1,
    "AwayTeamScore": 1
  },
  {
    "DateUtc": "31/08/22",
    "HomeTeam": "Sampdoria",
    "AwayTeam": "Lazio",
    "HomeTeamScore": 1,
    "AwayTeamScore": 1
  },
  {
    "DateUtc": "31/08/22",
    "HomeTeam": "Udinese",
    "AwayTeam": "Fiorentina",
    "HomeTeamScore": 1,
    "AwayTeamScore": 0
  },
  {
    "DateUtc": "31/08/22",
    "HomeTeam": "Juventus",
    "AwayTeam": "Spezia",
    "HomeTeamScore": 2,
    "AwayTeamScore": 0
  },
  {
    "DateUtc": "31/08/22",
    "HomeTeam": "Napoli",
    "AwayTeam": "Lecce",
    "HomeTeamScore": 1,
    "AwayTeamScore": 1
  },
  {
    "DateUtc": "01/09/22",
    "HomeTeam": "Atalanta",
    "AwayTeam": "Torino",
    "HomeTeamScore": 3,
    "AwayTeamScore": 1
  },
  {
    "DateUtc": "01/09/22",
    "HomeTeam": "Bologna",
    "AwayTeam": "Salernitana",
    "HomeTeamScore": 1,
    "AwayTeamScore": 1
  },
  {
    "DateUtc": "03/09/22",
    "HomeTeam": "Fiorentina",
    "AwayTeam": "Juventus",
    "HomeTeamScore": 1,
    "AwayTeamScore": 1
  },
  {
    "DateUtc": "03/09/22",
    "HomeTeam": "Milan",
    "AwayTeam": "Inter",
    "HomeTeamScore": 3,
    "AwayTeamScore": 2
  },
  {
    "DateUtc": "03/09/22",
    "HomeTeam": "Lazio",
    "AwayTeam": "Napoli",
    "HomeTeamScore": 1,
    "AwayTeamScore": 2
  },
  {
    "DateUtc": "04/09/22",
    "HomeTeam": "Cremonese",
    "AwayTeam": "Sassuolo",
    "HomeTeamScore": 0,
    "AwayTeamScore": 0
  },
  {
    "DateUtc": "04/09/22",
    "HomeTeam": "Spezia",
    "AwayTeam": "Bologna",
    "HomeTeamScore": 2,
    "AwayTeamScore": 2
  },
  {
    "DateUtc": "04/09/22",
    "HomeTeam": "Verona",
    "AwayTeam": "Sampdoria",
    "HomeTeamScore": 2,
    "AwayTeamScore": 1
  },
  {
    "DateUtc": "04/09/22",
    "HomeTeam": "Udinese",
    "AwayTeam": "Roma",
    "HomeTeamScore": 4,
    "AwayTeamScore": 0
  },
  {
    "DateUtc": "05/09/22",
    "HomeTeam": "Monza",
    "AwayTeam": "Atalanta",
    "HomeTeamScore": 0,
    "AwayTeamScore": 2
  },
  {
    "DateUtc": "05/09/22",
    "HomeTeam": "Salernitana",
    "AwayTeam": "Empoli",
    "HomeTeamScore": 2,
    "AwayTeamScore": 2
  },
  {
    "DateUtc": "05/09/22",
    "HomeTeam": "Torino",
    "AwayTeam": "Lecce",
    "HomeTeamScore": 1,
    "AwayTeamScore": 0
  },
  {
    "DateUtc": "10/09/22",
    "HomeTeam": "Napoli",
    "AwayTeam": "Spezia",
    "HomeTeamScore": 1,
    "AwayTeamScore": 0
  },
  {
    "DateUtc": "10/09/22",
    "HomeTeam": "Inter",
    "AwayTeam": "Torino",
    "HomeTeamScore": 1,
    "AwayTeamScore": 0
  },
  {
    "DateUtc": "10/09/22",
    "HomeTeam": "Sampdoria",
    "AwayTeam": "Milan",
    "HomeTeamScore": 1,
    "AwayTeamScore": 2
  },
  {
    "DateUtc": "11/09/22",
    "HomeTeam": "Atalanta",
    "AwayTeam": "Cremonese",
    "HomeTeamScore": 1,
    "AwayTeamScore": 1
  },
  {
    "DateUtc": "11/09/22",
    "HomeTeam": "Bologna",
    "AwayTeam": "Fiorentina",
    "HomeTeamScore": 2,
    "AwayTeamScore": 1
  },
  {
    "DateUtc": "11/09/22",
    "HomeTeam": "Lecce",
    "AwayTeam": "Monza",
    "HomeTeamScore": 1,
    "AwayTeamScore": 1
  },
  {
    "DateUtc": "11/09/22",
    "HomeTeam": "Sassuolo",
    "AwayTeam": "Udinese",
    "HomeTeamScore": 1,
    "AwayTeamScore": 3
  },
  {
    "DateUtc": "11/09/22",
    "HomeTeam": "Lazio",
    "AwayTeam": "Verona",
    "HomeTeamScore": 2,
    "AwayTeamScore": 0
  },
  {
    "DateUtc": "11/09/22",
    "HomeTeam": "Juventus",
    "AwayTeam": "Salernitana",
    "HomeTeamScore": 2,
    "AwayTeamScore": 2
  },
  {
    "DateUtc": "12/09/22",
    "HomeTeam": "Empoli",
    "AwayTeam": "Roma",
    "HomeTeamScore": 1,
    "AwayTeamScore": 2
  },
  {
    "DateUtc": "16/09/22",
    "HomeTeam": "Salernitana",
    "AwayTeam": "Lecce",
    "HomeTeamScore": 1,
    "AwayTeamScore": 2
  },
  {
    "DateUtc": "17/09/22",
    "HomeTeam": "Bologna",
    "AwayTeam": "Empoli",
    "HomeTeamScore": 0,
    "AwayTeamScore": 1
  },
  {
    "DateUtc": "17/09/22",
    "HomeTeam": "Spezia",
    "AwayTeam": "Sampdoria",
    "HomeTeamScore": 2,
    "AwayTeamScore": 1
  },
  {
    "DateUtc": "17/09/22",
    "HomeTeam": "Torino",
    "AwayTeam": "Sassuolo",
    "HomeTeamScore": 0,
    "AwayTeamScore": 1
  },
  {
    "DateUtc": "18/09/22",
    "HomeTeam": "Udinese",
    "AwayTeam": "Inter",
    "HomeTeamScore": 3,
    "AwayTeamScore": 1
  },
  {
    "DateUtc": "18/09/22",
    "HomeTeam": "Cremonese",
    "AwayTeam": "Lazio",
    "HomeTeamScore": 0,
    "AwayTeamScore": 4
  },
  {
    "DateUtc": "18/09/22",
    "HomeTeam": "Fiorentina",
    "AwayTeam": "Verona",
    "HomeTeamScore": 2,
    "AwayTeamScore": 0
  },
  {
    "DateUtc": "18/09/22",
    "HomeTeam": "Monza",
    "AwayTeam": "Juventus",
    "HomeTeamScore": 1,
    "AwayTeamScore": 0
  },
  {
    "DateUtc": "18/09/22",
    "HomeTeam": "Roma",
    "AwayTeam": "Atalanta",
    "HomeTeamScore": 0,
    "AwayTeamScore": 1
  },
  {
    "DateUtc": "18/09/22",
    "HomeTeam": "Milan",
    "AwayTeam": "Napoli",
    "HomeTeamScore": 1,
    "AwayTeamScore": 2
  },
  {
    "DateUtc": "01/10/22",
    "HomeTeam": "Napoli",
    "AwayTeam": "Torino",
    "HomeTeamScore": 3,
    "AwayTeamScore": 1
  },
  {
    "DateUtc": "01/10/22",
    "HomeTeam": "Inter",
    "AwayTeam": "Roma",
    "HomeTeamScore": 1,
    "AwayTeamScore": 2
  },
  {
    "DateUtc": "01/10/22",
    "HomeTeam": "Empoli",
    "AwayTeam": "Milan",
    "HomeTeamScore": 1,
    "AwayTeamScore": 3
  },
  {
    "DateUtc": "02/10/22",
    "HomeTeam": "Lazio",
    "AwayTeam": "Spezia",
    "HomeTeamScore": 4,
    "AwayTeamScore": 0
  },
  {
    "DateUtc": "02/10/22",
    "HomeTeam": "Lecce",
    "AwayTeam": "Cremonese",
    "HomeTeamScore": 1,
    "AwayTeamScore": 1
  },
  {
    "DateUtc": "02/10/22",
    "HomeTeam": "Sampdoria",
    "AwayTeam": "Monza",
    "HomeTeamScore": 0,
    "AwayTeamScore": 3
  },
  {
    "DateUtc": "02/10/22",
    "HomeTeam": "Sassuolo",
    "AwayTeam": "Salernitana",
    "HomeTeamScore": 5,
    "AwayTeamScore": 0
  },
  {
    "DateUtc": "02/10/22",
    "HomeTeam": "Atalanta",
    "AwayTeam": "Fiorentina",
    "HomeTeamScore": 1,
    "AwayTeamScore": 0
  },
  {
    "DateUtc": "02/10/22",
    "HomeTeam": "Juventus",
    "AwayTeam": "Bologna",
    "HomeTeamScore": 3,
    "AwayTeamScore": 0
  },
  {
    "DateUtc": "03/10/22",
    "HomeTeam": "Verona",
    "AwayTeam": "Udinese",
    "HomeTeamScore": 1,
    "AwayTeamScore": 2
  },
  {
    "DateUtc": "08/10/22",
    "HomeTeam": "Sassuolo",
    "AwayTeam": "Inter",
    "HomeTeamScore": 1,
    "AwayTeamScore": 2
  },
  {
    "DateUtc": "08/10/22",
    "HomeTeam": "Milan",
    "AwayTeam": "Juventus",
    "HomeTeamScore": 2,
    "AwayTeamScore": 0
  },
  {
    "DateUtc": "08/10/22",
    "HomeTeam": "Bologna",
    "AwayTeam": "Sampdoria",
    "HomeTeamScore": 1,
    "AwayTeamScore": 1
  },
  {
    "DateUtc": "09/10/22",
    "HomeTeam": "Torino",
    "AwayTeam": "Empoli",
    "HomeTeamScore": 1,
    "AwayTeamScore": 1
  },
  {
    "DateUtc": "09/10/22",
    "HomeTeam": "Monza",
    "AwayTeam": "Spezia",
    "HomeTeamScore": 2,
    "AwayTeamScore": 0
  },
  {
    "DateUtc": "09/10/22",
    "HomeTeam": "Salernitana",
    "AwayTeam": "Verona",
    "HomeTeamScore": 2,
    "AwayTeamScore": 1
  },
  {
    "DateUtc": "09/10/22",
    "HomeTeam": "Udinese",
    "AwayTeam": "Atalanta",
    "HomeTeamScore": 2,
    "AwayTeamScore": 2
  },
  {
    "DateUtc": "09/10/22",
    "HomeTeam": "Cremonese",
    "AwayTeam": "Napoli",
    "HomeTeamScore": 1,
    "AwayTeamScore": 4
  },
  {
    "DateUtc": "09/10/22",
    "HomeTeam": "Roma",
    "AwayTeam": "Lecce",
    "HomeTeamScore": 2,
    "AwayTeamScore": 1
  },
  {
    "DateUtc": "10/10/22",
    "HomeTeam": "Fiorentina",
    "AwayTeam": "Lazio",
    "HomeTeamScore": 0,
    "AwayTeamScore": 4
  },
  {
    "DateUtc": "15/10/22",
    "HomeTeam": "Empoli",
    "AwayTeam": "Monza",
    "HomeTeamScore": 1,
    "AwayTeamScore": 0
  },
  {
    "DateUtc": "15/10/22",
    "HomeTeam": "Torino",
    "AwayTeam": "Juventus",
    "HomeTeamScore": 0,
    "AwayTeamScore": 1
  },
  {
    "DateUtc": "15/10/22",
    "HomeTeam": "Atalanta",
    "AwayTeam": "Sassuolo",
    "HomeTeamScore": 2,
    "AwayTeamScore": 1
  },
  {
    "DateUtc": "16/10/22",
    "HomeTeam": "Inter",
    "AwayTeam": "Salernitana",
    "HomeTeamScore": 2,
    "AwayTeamScore": 0
  },
  {
    "DateUtc": "16/10/22",
    "HomeTeam": "Lazio",
    "AwayTeam": "Udinese",
    "HomeTeamScore": 0,
    "AwayTeamScore": 0
  },
  {
    "DateUtc": "16/10/22",
    "HomeTeam": "Spezia",
    "AwayTeam": "Cremonese",
    "HomeTeamScore": 2,
    "AwayTeamScore": 2
  },
  {
    "DateUtc": "16/10/22",
    "HomeTeam": "Napoli",
    "AwayTeam": "Bologna",
    "HomeTeamScore": 3,
    "AwayTeamScore": 2
  },
  {
    "DateUtc": "16/10/22",
    "HomeTeam": "Verona",
    "AwayTeam": "Milan",
    "HomeTeamScore": 1,
    "AwayTeamScore": 2
  },
  {
    "DateUtc": "17/10/22",
    "HomeTeam": "Sampdoria",
    "AwayTeam": "Roma",
    "HomeTeamScore": 0,
    "AwayTeamScore": 1
  },
  {
    "DateUtc": "17/10/22",
    "HomeTeam": "Lecce",
    "AwayTeam": "Fiorentina",
    "HomeTeamScore": 1,
    "AwayTeamScore": 1
  },
  {
    "DateUtc": "21/10/22",
    "HomeTeam": "Juventus",
    "AwayTeam": "Empoli",
    "HomeTeamScore": 4,
    "AwayTeamScore": 0
  },
  {
    "DateUtc": "22/10/22",
    "HomeTeam": "Salernitana",
    "AwayTeam": "Spezia",
    "HomeTeamScore": 1,
    "AwayTeamScore": 0
  },
  {
    "DateUtc": "22/10/22",
    "HomeTeam": "Milan",
    "AwayTeam": "Monza",
    "HomeTeamScore": 4,
    "AwayTeamScore": 1
  },
  {
    "DateUtc": "22/10/22",
    "HomeTeam": "Fiorentina",
    "AwayTeam": "Inter",
    "HomeTeamScore": 3,
    "AwayTeamScore": 4
  },
  {
    "DateUtc": "23/10/22",
    "HomeTeam": "Udinese",
    "AwayTeam": "Torino",
    "HomeTeamScore": 1,
    "AwayTeamScore": 2
  },
  {
    "DateUtc": "23/10/22",
    "HomeTeam": "Bologna",
    "AwayTeam": "Lecce",
    "HomeTeamScore": 2,
    "AwayTeamScore": 0
  },
  {
    "DateUtc": "23/10/22",
    "HomeTeam": "Atalanta",
    "AwayTeam": "Lazio",
    "HomeTeamScore": 0,
    "AwayTeamScore": 2
  },
  {
    "DateUtc": "23/10/22",
    "HomeTeam": "Roma",
    "AwayTeam": "Napoli",
    "HomeTeamScore": 0,
    "AwayTeamScore": 1
  },
  {
    "DateUtc": "24/10/22",
    "HomeTeam": "Cremonese",
    "AwayTeam": "Sampdoria",
    "HomeTeamScore": 0,
    "AwayTeamScore": 1
  },
  {
    "DateUtc": "24/10/22",
    "HomeTeam": "Sassuolo",
    "AwayTeam": "Verona",
    "HomeTeamScore": 2,
    "AwayTeamScore": 1
  },
  {
    "DateUtc": "29/10/22",
    "HomeTeam": "Napoli",
    "AwayTeam": "Sassuolo",
    "HomeTeamScore": 4,
    "AwayTeamScore": 0
  },
  {
    "DateUtc": "29/10/22",
    "HomeTeam": "Lecce",
    "AwayTeam": "Juventus",
    "HomeTeamScore": 0,
    "AwayTeamScore": 1
  },
  {
    "DateUtc": "29/10/22",
    "HomeTeam": "Inter",
    "AwayTeam": "Sampdoria",
    "HomeTeamScore": 3,
    "AwayTeamScore": 0
  },
  {
    "DateUtc": "30/10/22",
    "HomeTeam": "Empoli",
    "AwayTeam": "Atalanta",
    "HomeTeamScore": 0,
    "AwayTeamScore": 2
  },
  {
    "DateUtc": "30/10/22",
    "HomeTeam": "Cremonese",
    "AwayTeam": "Udinese",
    "HomeTeamScore": 0,
    "AwayTeamScore": 0
  },
  {
    "DateUtc": "30/10/22",
    "HomeTeam": "Spezia",
    "AwayTeam": "Fiorentina",
    "HomeTeamScore": 1,
    "AwayTeamScore": 2
  },
  {
    "DateUtc": "30/10/22",
    "HomeTeam": "Lazio",
    "AwayTeam": "Salernitana",
    "HomeTeamScore": 1,
    "AwayTeamScore": 3
  },
  {
    "DateUtc": "30/10/22",
    "HomeTeam": "Torino",
    "AwayTeam": "Milan",
    "HomeTeamScore": 2,
    "AwayTeamScore": 1
  },
  {
    "DateUtc": "31/10/22",
    "HomeTeam": "Verona",
    "AwayTeam": "Roma",
    "HomeTeamScore": 1,
    "AwayTeamScore": 3
  },
  {
    "DateUtc": "31/10/22",
    "HomeTeam": "Monza",
    "AwayTeam": "Bologna",
    "HomeTeamScore": 1,
    "AwayTeamScore": 2
  },
  {
    "DateUtc": "04/11/22",
    "HomeTeam": "Udinese",
    "AwayTeam": "Lecce",
    "HomeTeamScore": 1,
    "AwayTeamScore": 1
  },
  {
    "DateUtc": "05/11/22",
    "HomeTeam": "Empoli",
    "AwayTeam": "Sassuolo",
    "HomeTeamScore": 1,
    "AwayTeamScore": 0
  },
  {
    "DateUtc": "05/11/22",
    "HomeTeam": "Salernitana",
    "AwayTeam": "Cremonese",
    "HomeTeamScore": 2,
    "AwayTeamScore": 2
  },
  {
    "DateUtc": "05/11/22",
    "HomeTeam": "Atalanta",
    "AwayTeam": "Napoli",
    "HomeTeamScore": 1,
    "AwayTeamScore": 2
  },
  {
    "DateUtc": "05/11/22",
    "HomeTeam": "Milan",
    "AwayTeam": "Spezia",
    "HomeTeamScore": 2,
    "AwayTeamScore": 1
  },
  {
    "DateUtc": "06/11/22",
    "HomeTeam": "Bologna",
    "AwayTeam": "Torino",
    "HomeTeamScore": 2,
    "AwayTeamScore": 1
  },
  {
    "DateUtc": "06/11/22",
    "HomeTeam": "Monza",
    "AwayTeam": "Verona",
    "HomeTeamScore": 2,
    "AwayTeamScore": 0
  },
  {
    "DateUtc": "06/11/22",
    "HomeTeam": "Sampdoria",
    "AwayTeam": "Fiorentina",
    "HomeTeamScore": 0,
    "AwayTeamScore": 2
  },
  {
    "DateUtc": "06/11/22",
    "HomeTeam": "Roma",
    "AwayTeam": "Lazio",
    "HomeTeamScore": 0,
    "AwayTeamScore": 1
  },
  {
    "DateUtc": "06/11/22",
    "HomeTeam": "Juventus",
    "AwayTeam": "Inter",
    "HomeTeamScore": 2,
    "AwayTeamScore": 0
  },
  {
    "DateUtc": "08/11/22",
    "HomeTeam": "Napoli",
    "AwayTeam": "Empoli",
    "HomeTeamScore": 2,
    "AwayTeamScore": 0
  },
  {
    "DateUtc": "08/11/22",
    "HomeTeam": "Spezia",
    "AwayTeam": "Udinese",
    "HomeTeamScore": 1,
    "AwayTeamScore": 1
  },
  {
    "DateUtc": "08/11/22",
    "HomeTeam": "Cremonese",
    "AwayTeam": "Milan",
    "HomeTeamScore": 0,
    "AwayTeamScore": 0
  },
  {
    "DateUtc": "09/11/22",
    "HomeTeam": "Lecce",
    "AwayTeam": "Atalanta",
    "HomeTeamScore": 2,
    "AwayTeamScore": 1
  },
  {
    "DateUtc": "09/11/22",
    "HomeTeam": "Sassuolo",
    "AwayTeam": "Roma",
    "HomeTeamScore": 1,
    "AwayTeamScore": 1
  },
  {
    "DateUtc": "09/11/22",
    "HomeTeam": "Fiorentina",
    "AwayTeam": "Salernitana",
    "HomeTeamScore": 2,
    "AwayTeamScore": 1
  },
  {
    "DateUtc": "09/11/22",
    "HomeTeam": "Inter",
    "AwayTeam": "Bologna",
    "HomeTeamScore": 6,
    "AwayTeamScore": 1
  },
  {
    "DateUtc": "09/11/22",
    "HomeTeam": "Torino",
    "AwayTeam": "Sampdoria",
    "HomeTeamScore": 2,
    "AwayTeamScore": 0
  },
  {
    "DateUtc": "10/11/22",
    "HomeTeam": "Verona",
    "AwayTeam": "Juventus",
    "HomeTeamScore": 0,
    "AwayTeamScore": 1
  },
  {
    "DateUtc": "10/11/22",
    "HomeTeam": "Lazio",
    "AwayTeam": "Monza",
    "HomeTeamScore": 1,
    "AwayTeamScore": 0
  },
  {
    "DateUtc": "11/11/22",
    "HomeTeam": "Empoli",
    "AwayTeam": "Cremonese",
    "HomeTeamScore": 2,
    "AwayTeamScore": 0
  },
  {
    "DateUtc": "12/11/22",
    "HomeTeam": "Napoli",
    "AwayTeam": "Udinese",
    "HomeTeamScore": 3,
    "AwayTeamScore": 2
  },
  {
    "DateUtc": "12/11/22",
    "HomeTeam": "Sampdoria",
    "AwayTeam": "Lecce",
    "HomeTeamScore": 0,
    "AwayTeamScore": 2
  },
  {
    "DateUtc": "12/11/22",
    "HomeTeam": "Bologna",
    "AwayTeam": "Sassuolo",
    "HomeTeamScore": 3,
    "AwayTeamScore": 0
  },
  {
    "DateUtc": "13/11/22",
    "HomeTeam": "Atalanta",
    "AwayTeam": "Inter",
    "HomeTeamScore": 2,
    "AwayTeamScore": 3
  },
  {
    "DateUtc": "13/11/22",
    "HomeTeam": "Monza",
    "AwayTeam": "Salernitana",
    "HomeTeamScore": 3,
    "AwayTeamScore": 0
  },
  {
    "DateUtc": "13/11/22",
    "HomeTeam": "Roma",
    "AwayTeam": "Torino",
    "HomeTeamScore": 1,
    "AwayTeamScore": 1
  },
  {
    "DateUtc": "13/11/22",
    "HomeTeam": "Verona",
    "AwayTeam": "Spezia",
    "HomeTeamScore": 1,
    "AwayTeamScore": 2
  },
  {
    "DateUtc": "13/11/22",
    "HomeTeam": "Milan",
    "AwayTeam": "Fiorentina",
    "HomeTeamScore": 2,
    "AwayTeamScore": 1
  },
  {
    "DateUtc": "13/11/22",
    "HomeTeam": "Juventus",
    "AwayTeam": "Lazio",
    "HomeTeamScore": 3,
    "AwayTeamScore": 0
  },
  {
    "DateUtc": "04/01/23",
    "HomeTeam": "Salernitana",
    "AwayTeam": "Milan",
    "HomeTeamScore": 1,
    "AwayTeamScore": 2
  },
  {
    "DateUtc": "04/01/23",
    "HomeTeam": "Sassuolo",
    "AwayTeam": "Sampdoria",
    "HomeTeamScore": 1,
    "AwayTeamScore": 2
  },
  {
    "DateUtc": "04/01/23",
    "HomeTeam": "Spezia",
    "AwayTeam": "Atalanta",
    "HomeTeamScore": 2,
    "AwayTeamScore": 2
  },
  {
    "DateUtc": "04/01/23",
    "HomeTeam": "Torino",
    "AwayTeam": "Verona",
    "HomeTeamScore": 1,
    "AwayTeamScore": 1
  },
  {
    "DateUtc": "04/01/23",
    "HomeTeam": "Lecce",
    "AwayTeam": "Lazio",
    "HomeTeamScore": 2,
    "AwayTeamScore": 1
  },
  {
    "DateUtc": "04/01/23",
    "HomeTeam": "Roma",
    "AwayTeam": "Bologna",
    "HomeTeamScore": 1,
    "AwayTeamScore": 0
  },
  {
    "DateUtc": "04/01/23",
    "HomeTeam": "Cremonese",
    "AwayTeam": "Juventus",
    "HomeTeamScore": 0,
    "AwayTeamScore": 1
  },
  {
    "DateUtc": "04/01/23",
    "HomeTeam": "Fiorentina",
    "AwayTeam": "Monza",
    "HomeTeamScore": 1,
    "AwayTeamScore": 1
  },
  {
    "DateUtc": "04/01/23",
    "HomeTeam": "Inter",
    "AwayTeam": "Napoli",
    "HomeTeamScore": 1,
    "AwayTeamScore": 0
  },
  {
    "DateUtc": "04/01/23",
    "HomeTeam": "Udinese",
    "AwayTeam": "Empoli",
    "HomeTeamScore": 1,
    "AwayTeamScore": 1
  },
  {
    "DateUtc": "07/01/23",
    "HomeTeam": "Fiorentina",
    "AwayTeam": "Sassuolo",
    "HomeTeamScore": 2,
    "AwayTeamScore": 1
  },
  {
    "DateUtc": "07/01/23",
    "HomeTeam": "Juventus",
    "AwayTeam": "Udinese",
    "HomeTeamScore": 1,
    "AwayTeamScore": 0
  },
  {
    "DateUtc": "07/01/23",
    "HomeTeam": "Monza",
    "AwayTeam": "Inter",
    "HomeTeamScore": 2,
    "AwayTeamScore": 2
  },
  {
    "DateUtc": "08/01/23",
    "HomeTeam": "Salernitana",
    "AwayTeam": "Torino",
    "HomeTeamScore": 1,
    "AwayTeamScore": 1
  },
  {
    "DateUtc": "08/01/23",
    "HomeTeam": "Lazio",
    "AwayTeam": "Empoli",
    "HomeTeamScore": 2,
    "AwayTeamScore": 2
  },
  {
    "DateUtc": "08/01/23",
    "HomeTeam": "Spezia",
    "AwayTeam": "Lecce",
    "HomeTeamScore": 0,
    "AwayTeamScore": 0
  },
  {
    "DateUtc": "08/01/23",
    "HomeTeam": "Sampdoria",
    "AwayTeam": "Napoli",
    "HomeTeamScore": 0,
    "AwayTeamScore": 2
  },
  {
    "DateUtc": "08/01/23",
    "HomeTeam": "Milan",
    "AwayTeam": "Roma",
    "HomeTeamScore": 2,
    "AwayTeamScore": 2
  },
  {
    "DateUtc": "09/01/23",
    "HomeTeam": "Verona",
    "AwayTeam": "Cremonese",
    "HomeTeamScore": 2,
    "AwayTeamScore": 0
  },
  {
    "DateUtc": "09/01/23",
    "HomeTeam": "Bologna",
    "AwayTeam": "Atalanta",
    "HomeTeamScore": 1,
    "AwayTeamScore": 2
  },
  {
    "DateUtc": "13/01/23",
    "HomeTeam": "Napoli",
    "AwayTeam": "Juventus",
    "HomeTeamScore": 5,
    "AwayTeamScore": 1
  },
  {
    "DateUtc": "14/01/23",
    "HomeTeam": "Cremonese",
    "AwayTeam": "Monza",
    "HomeTeamScore": 2,
    "AwayTeamScore": 3
  },
  {
    "DateUtc": "14/01/23",
    "HomeTeam": "Lecce",
    "AwayTeam": "Milan",
    "HomeTeamScore": 2,
    "AwayTeamScore": 2
  },
  {
    "DateUtc": "14/01/23",
    "HomeTeam": "Inter",
    "AwayTeam": "Verona",
    "HomeTeamScore": 1,
    "AwayTeamScore": 0
  },
  {
    "DateUtc": "15/01/23",
    "HomeTeam": "Sassuolo",
    "AwayTeam": "Lazio",
    "HomeTeamScore": 0,
    "AwayTeamScore": 2
  },
  {
    "DateUtc": "15/01/23",
    "HomeTeam": "Torino",
    "AwayTeam": "Spezia",
    "HomeTeamScore": 0,
    "AwayTeamScore": 1
  },
  {
    "DateUtc": "15/01/23",
    "HomeTeam": "Udinese",
    "AwayTeam": "Bologna",
    "HomeTeamScore": 1,
    "AwayTeamScore": 2
  },
  {
    "DateUtc": "15/01/23",
    "HomeTeam": "Atalanta",
    "AwayTeam": "Salernitana",
    "HomeTeamScore": 8,
    "AwayTeamScore": 2
  },
  {
    "DateUtc": "15/01/23",
    "HomeTeam": "Roma",
    "AwayTeam": "Fiorentina",
    "HomeTeamScore": 2,
    "AwayTeamScore": 0
  },
  {
    "DateUtc": "16/01/23",
    "HomeTeam": "Empoli",
    "AwayTeam": "Sampdoria",
    "HomeTeamScore": 1,
    "AwayTeamScore": 0
  },
  {
    "DateUtc": "21/01/23",
    "HomeTeam": "Verona",
    "AwayTeam": "Lecce",
    "HomeTeamScore": 2,
    "AwayTeamScore": 0
  },
  {
    "DateUtc": "21/01/23",
    "HomeTeam": "Salernitana",
    "AwayTeam": "Napoli",
    "HomeTeamScore": 0,
    "AwayTeamScore": 2
  },
  {
    "DateUtc": "21/01/23",
    "HomeTeam": "Fiorentina",
    "AwayTeam": "Torino",
    "HomeTeamScore": 0,
    "AwayTeamScore": 1
  },
  {
    "DateUtc": "22/01/23",
    "HomeTeam": "Sampdoria",
    "AwayTeam": "Udinese",
    "HomeTeamScore": 0,
    "AwayTeamScore": 1
  },
  {
    "DateUtc": "22/01/23",
    "HomeTeam": "Monza",
    "AwayTeam": "Sassuolo",
    "HomeTeamScore": 1,
    "AwayTeamScore": 1
  },
  {
    "DateUtc": "22/01/23",
    "HomeTeam": "Spezia",
    "AwayTeam": "Roma",
    "HomeTeamScore": 0,
    "AwayTeamScore": 2
  },
  {
    "DateUtc": "22/01/23",
    "HomeTeam": "Juventus",
    "AwayTeam": "Atalanta",
    "HomeTeamScore": 3,
    "AwayTeamScore": 3
  },
  {
    "DateUtc": "23/01/23",
    "HomeTeam": "Bologna",
    "AwayTeam": "Cremonese",
    "HomeTeamScore": 1,
    "AwayTeamScore": 1
  },
  {
    "DateUtc": "23/01/23",
    "HomeTeam": "Inter",
    "AwayTeam": "Empoli",
    "HomeTeamScore": 0,
    "AwayTeamScore": 1
  },
  {
    "DateUtc": "24/01/23",
    "HomeTeam": "Lazio",
    "AwayTeam": "Milan",
    "HomeTeamScore": 4,
    "AwayTeamScore": 0
  },
  {
    "DateUtc": "27/01/23",
    "HomeTeam": "Bologna",
    "AwayTeam": "Spezia",
    "HomeTeamScore": 2,
    "AwayTeamScore": 0
  },
  {
    "DateUtc": "27/01/23",
    "HomeTeam": "Lecce",
    "AwayTeam": "Salernitana",
    "HomeTeamScore": 1,
    "AwayTeamScore": 2
  },
  {
    "DateUtc": "28/01/23",
    "HomeTeam": "Empoli",
    "AwayTeam": "Torino",
    "HomeTeamScore": 2,
    "AwayTeamScore": 2
  },
  {
    "DateUtc": "28/01/23",
    "HomeTeam": "Cremonese",
    "AwayTeam": "Inter",
    "HomeTeamScore": 1,
    "AwayTeamScore": 2
  },
  {
    "DateUtc": "28/01/23",
    "HomeTeam": "Atalanta",
    "AwayTeam": "Sampdoria",
    "HomeTeamScore": 2,
    "AwayTeamScore": 0
  },
  {
    "DateUtc": "29/01/23",
    "HomeTeam": "Milan",
    "AwayTeam": "Sassuolo",
    "HomeTeamScore": 2,
    "AwayTeamScore": 5
  },
  {
    "DateUtc": "29/01/23",
    "HomeTeam": "Juventus",
    "AwayTeam": "Monza",
    "HomeTeamScore": 0,
    "AwayTeamScore": 2
  },
  {
    "DateUtc": "29/01/23",
    "HomeTeam": "Lazio",
    "AwayTeam": "Fiorentina",
    "HomeTeamScore": 1,
    "AwayTeamScore": 1
  },
  {
    "DateUtc": "29/01/23",
    "HomeTeam": "Napoli",
    "AwayTeam": "Roma",
    "HomeTeamScore": 2,
    "AwayTeamScore": 1
  },
  {
    "DateUtc": "30/01/23",
    "HomeTeam": "Udinese",
    "AwayTeam": "Verona",
    "HomeTeamScore": 1,
    "AwayTeamScore": 1
  },
  {
    "DateUtc": "04/02/23",
    "HomeTeam": "Cremonese",
    "AwayTeam": "Lecce",
    "HomeTeamScore": 0,
    "AwayTeamScore": 2
  },
  {
    "DateUtc": "04/02/23",
    "HomeTeam": "Roma",
    "AwayTeam": "Empoli",
    "HomeTeamScore": 2,
    "AwayTeamScore": 0
  },
  {
    "DateUtc": "04/02/23",
    "HomeTeam": "Sassuolo",
    "AwayTeam": "Atalanta",
    "HomeTeamScore": 1,
    "AwayTeamScore": 0
  },
  {
    "DateUtc": "05/02/23",
    "HomeTeam": "Spezia",
    "AwayTeam": "Napoli",
    "HomeTeamScore": 0,
    "AwayTeamScore": 3
  },
  {
    "DateUtc": "05/02/23",
    "HomeTeam": "Torino",
    "AwayTeam": "Udinese",
    "HomeTeamScore": 1,
    "AwayTeamScore": 0
  },
  {
    "DateUtc": "05/02/23",
    "HomeTeam": "Fiorentina",
    "AwayTeam": "Bologna",
    "HomeTeamScore": 1,
    "AwayTeamScore": 2
  },
  {
    "DateUtc": "05/02/23",
    "HomeTeam": "Inter",
    "AwayTeam": "Milan",
    "HomeTeamScore": 1,
    "AwayTeamScore": 0
  },
  {
    "DateUtc": "06/02/23",
    "HomeTeam": "Verona",
    "AwayTeam": "Lazio",
    "HomeTeamScore": 1,
    "AwayTeamScore": 1
  },
  {
    "DateUtc": "06/02/23",
    "HomeTeam": "Monza",
    "AwayTeam": "Sampdoria",
    "HomeTeamScore": 2,
    "AwayTeamScore": 2
  },
  {
    "DateUtc": "07/02/23",
    "HomeTeam": "Salernitana",
    "AwayTeam": "Juventus",
    "HomeTeamScore": 0,
    "AwayTeamScore": 3
  },
  {
    "DateUtc": "10/02/23",
    "HomeTeam": "Milan",
    "AwayTeam": "Torino",
    "HomeTeamScore": 1,
    "AwayTeamScore": 0
  },
  {
    "DateUtc": "11/02/23",
    "HomeTeam": "Empoli",
    "AwayTeam": "Spezia",
    "HomeTeamScore": 2,
    "AwayTeamScore": 2
  },
  {
    "DateUtc": "11/02/23",
    "HomeTeam": "Lecce",
    "AwayTeam": "Roma",
    "HomeTeamScore": 1,
    "AwayTeamScore": 1
  },
  {
    "DateUtc": "11/02/23",
    "HomeTeam": "Lazio",
    "AwayTeam": "Atalanta",
    "HomeTeamScore": 0,
    "AwayTeamScore": 2
  },
  {
    "DateUtc": "12/02/23",
    "HomeTeam": "Udinese",
    "AwayTeam": "Sassuolo",
    "HomeTeamScore": 2,
    "AwayTeamScore": 2
  },
  {
    "DateUtc": "12/02/23",
    "HomeTeam": "Bologna",
    "AwayTeam": "Monza",
    "HomeTeamScore": 0,
    "AwayTeamScore": 1
  },
  {
    "DateUtc": "12/02/23",
    "HomeTeam": "Juventus",
    "AwayTeam": "Fiorentina",
    "HomeTeamScore": 1,
    "AwayTeamScore": 0
  },
  {
    "DateUtc": "12/02/23",
    "HomeTeam": "Napoli",
    "AwayTeam": "Cremonese",
    "HomeTeamScore": 3,
    "AwayTeamScore": 0
  },
  {
    "DateUtc": "13/02/23",
    "HomeTeam": "Verona",
    "AwayTeam": "Salernitana",
    "HomeTeamScore": 1,
    "AwayTeamScore": 0
  },
  {
    "DateUtc": "13/02/23",
    "HomeTeam": "Sampdoria",
    "AwayTeam": "Inter",
    "HomeTeamScore": 0,
    "AwayTeamScore": 0
  },
  {
    "DateUtc": "17/02/23",
    "HomeTeam": "Sassuolo",
    "AwayTeam": "Napoli",
    "HomeTeamScore": 0,
    "AwayTeamScore": 2
  },
  {
    "DateUtc": "18/02/23",
    "HomeTeam": "Sampdoria",
    "AwayTeam": "Bologna",
    "HomeTeamScore": 1,
    "AwayTeamScore": 2
  },
  {
    "DateUtc": "18/02/23",
    "HomeTeam": "Monza",
    "AwayTeam": "Milan",
    "HomeTeamScore": 0,
    "AwayTeamScore": 1
  },
  {
    "DateUtc": "18/02/23",
    "HomeTeam": "Inter",
    "AwayTeam": "Udinese",
    "HomeTeamScore": 3,
    "AwayTeamScore": 1
  },
  {
    "DateUtc": "19/02/23",
    "HomeTeam": "Atalanta",
    "AwayTeam": "Lecce",
    "HomeTeamScore": 1,
    "AwayTeamScore": 2
  },
  {
    "DateUtc": "19/02/23",
    "HomeTeam": "Fiorentina",
    "AwayTeam": "Empoli",
    "HomeTeamScore": 1,
    "AwayTeamScore": 1
  },
  {
    "DateUtc": "19/02/23",
    "HomeTeam": "Salernitana",
    "AwayTeam": "Lazio",
    "HomeTeamScore": 0,
    "AwayTeamScore": 2
  },
  {
    "DateUtc": "19/02/23",
    "HomeTeam": "Spezia",
    "AwayTeam": "Juventus",
    "HomeTeamScore": 0,
    "AwayTeamScore": 2
  },
  {
    "DateUtc": "19/02/23",
    "HomeTeam": "Roma",
    "AwayTeam": "Verona",
    "HomeTeamScore": 1,
    "AwayTeamScore": 0
  },
  {
    "DateUtc": "20/02/23",
    "HomeTeam": "Torino",
    "AwayTeam": "Cremonese",
    "HomeTeamScore": 2,
    "AwayTeamScore": 2
  },
  {
    "DateUtc": "25/02/23",
    "HomeTeam": "Empoli",
    "AwayTeam": "Napoli",
    "HomeTeamScore": 0,
    "AwayTeamScore": 2
  },
  {
    "DateUtc": "25/02/23",
    "HomeTeam": "Lecce",
    "AwayTeam": "Sassuolo",
    "HomeTeamScore": 0,
    "AwayTeamScore": 1
  },
  {
    "DateUtc": "26/02/23",
    "HomeTeam": "Bologna",
    "AwayTeam": "Inter",
    "HomeTeamScore": 1,
    "AwayTeamScore": 0
  },
  {
    "DateUtc": "26/02/23",
    "HomeTeam": "Salernitana",
    "AwayTeam": "Monza",
    "HomeTeamScore": 3,
    "AwayTeamScore": 0
  },
  {
    "DateUtc": "26/02/23",
    "HomeTeam": "Udinese",
    "AwayTeam": "Spezia",
    "HomeTeamScore": 2,
    "AwayTeamScore": 2
  },
  {
    "DateUtc": "26/02/23",
    "HomeTeam": "Milan",
    "AwayTeam": "Atalanta",
    "HomeTeamScore": 2,
    "AwayTeamScore": 0
  },
  {
    "DateUtc": "27/02/23",
    "HomeTeam": "Verona",
    "AwayTeam": "Fiorentina",
    "HomeTeamScore": 0,
    "AwayTeamScore": 3
  },
  {
    "DateUtc": "27/02/23",
    "HomeTeam": "Lazio",
    "AwayTeam": "Sampdoria",
    "HomeTeamScore": 1,
    "AwayTeamScore": 0
  },
  {
    "DateUtc": "28/02/23",
    "HomeTeam": "Cremonese",
    "AwayTeam": "Roma",
    "HomeTeamScore": 2,
    "AwayTeamScore": 1
  },
  {
    "DateUtc": "28/02/23",
    "HomeTeam": "Juventus",
    "AwayTeam": "Torino",
    "HomeTeamScore": 4,
    "AwayTeamScore": 2
  },
  {
    "DateUtc": "03/03/23",
    "HomeTeam": "Napoli",
    "AwayTeam": "Lazio",
    "HomeTeamScore": 0,
    "AwayTeamScore": 1
  },
  {
    "DateUtc": "04/03/23",
    "HomeTeam": "Monza",
    "AwayTeam": "Empoli",
    "HomeTeamScore": 2,
    "AwayTeamScore": 1
  },
  {
    "DateUtc": "04/03/23",
    "HomeTeam": "Atalanta",
    "AwayTeam": "Udinese",
    "HomeTeamScore": 0,
    "AwayTeamScore": 0
  },
  {
    "DateUtc": "04/03/23",
    "HomeTeam": "Fiorentina",
    "AwayTeam": "Milan",
    "HomeTeamScore": 2,
    "AwayTeamScore": 1
  },
  {
    "DateUtc": "05/03/23",
    "HomeTeam": "Spezia",
    "AwayTeam": "Verona",
    "HomeTeamScore": 0,
    "AwayTeamScore": 0
  },
  {
    "DateUtc": "05/03/23",
    "HomeTeam": "Sampdoria",
    "AwayTeam": "Salernitana",
    "HomeTeamScore": 0,
    "AwayTeamScore": 0
  },
  {
    "DateUtc": "05/03/23",
    "HomeTeam": "Inter",
    "AwayTeam": "Lecce",
    "HomeTeamScore": 2,
    "AwayTeamScore": 0
  },
  {
    "DateUtc": "05/03/23",
    "HomeTeam": "Roma",
    "AwayTeam": "Juventus",
    "HomeTeamScore": 1,
    "AwayTeamScore": 0
  },
  {
    "DateUtc": "06/03/23",
    "HomeTeam": "Sassuolo",
    "AwayTeam": "Cremonese",
    "HomeTeamScore": 3,
    "AwayTeamScore": 2
  },
  {
    "DateUtc": "06/03/23",
    "HomeTeam": "Torino",
    "AwayTeam": "Bologna",
    "HomeTeamScore": 1,
    "AwayTeamScore": 0
  },
  {
    "DateUtc": "10/03/23",
    "HomeTeam": "Spezia",
    "AwayTeam": "Inter",
    "HomeTeamScore": 2,
    "AwayTeamScore": 1
  },
  {
    "DateUtc": "11/03/23",
    "HomeTeam": "Empoli",
    "AwayTeam": "Udinese",
    "HomeTeamScore": 0,
    "AwayTeamScore": 1
  },
  {
    "DateUtc": "11/03/23",
    "HomeTeam": "Napoli",
    "AwayTeam": "Atalanta",
    "HomeTeamScore": 2,
    "AwayTeamScore": 0
  },
  {
    "DateUtc": "11/03/23",
    "HomeTeam": "Bologna",
    "AwayTeam": "Lazio",
    "HomeTeamScore": 0,
    "AwayTeamScore": 0
  },
  {
    "DateUtc": "12/03/23",
    "HomeTeam": "Lecce",
    "AwayTeam": "Torino",
    "HomeTeamScore": 0,
    "AwayTeamScore": 2
  },
  {
    "DateUtc": "12/03/23",
    "HomeTeam": "Cremonese",
    "AwayTeam": "Fiorentina",
    "HomeTeamScore": 0,
    "AwayTeamScore": 2
  },
  {
    "DateUtc": "12/03/23",
    "HomeTeam": "Verona",
    "AwayTeam": "Monza",
    "HomeTeamScore": 1,
    "AwayTeamScore": 1
  },
  {
    "DateUtc": "12/03/23",
    "HomeTeam": "Roma",
    "AwayTeam": "Sassuolo",
    "HomeTeamScore": 3,
    "AwayTeamScore": 4
  },
  {
    "DateUtc": "12/03/23",
    "HomeTeam": "Juventus",
    "AwayTeam": "Sampdoria",
    "HomeTeamScore": 4,
    "AwayTeamScore": 2
  },
  {
    "DateUtc": "13/03/23",
    "HomeTeam": "Milan",
    "AwayTeam": "Salernitana",
    "HomeTeamScore": 1,
    "AwayTeamScore": 1
  },
  {
    "DateUtc": "17/03/23",
    "HomeTeam": "Sassuolo",
    "AwayTeam": "Spezia",
    "HomeTeamScore": 1,
    "AwayTeamScore": 0
  },
  {
    "DateUtc": "17/03/23",
    "HomeTeam": "Atalanta",
    "AwayTeam": "Empoli",
    "HomeTeamScore": 2,
    "AwayTeamScore": 1
  },
  {
    "DateUtc": "18/03/23",
    "HomeTeam": "Monza",
    "AwayTeam": "Cremonese",
    "HomeTeamScore": 1,
    "AwayTeamScore": 1
  },
  {
    "DateUtc": "18/03/23",
    "HomeTeam": "Salernitana",
    "AwayTeam": "Bologna",
    "HomeTeamScore": 2,
    "AwayTeamScore": 2
  },
  {
    "DateUtc": "18/03/23",
    "HomeTeam": "Udinese",
    "AwayTeam": "Milan",
    "HomeTeamScore": 3,
    "AwayTeamScore": 1
  },
  {
    "DateUtc": "19/03/23",
    "HomeTeam": "Sampdoria",
    "AwayTeam": "Verona",
    "HomeTeamScore": 3,
    "AwayTeamScore": 1
  },
  {
    "DateUtc": "19/03/23",
    "HomeTeam": "Fiorentina",
    "AwayTeam": "Lecce",
    "HomeTeamScore": 1,
    "AwayTeamScore": 0
  },
  {
    "DateUtc": "19/03/23",
    "HomeTeam": "Torino",
    "AwayTeam": "Napoli",
    "HomeTeamScore": 0,
    "AwayTeamScore": 4
  },
  {
    "DateUtc": "19/03/23",
    "HomeTeam": "Lazio",
    "AwayTeam": "Roma",
    "HomeTeamScore": 1,
    "AwayTeamScore": 0
  },
  {
    "DateUtc": "19/03/23",
    "HomeTeam": "Inter",
    "AwayTeam": "Juventus",
    "HomeTeamScore": 0,
    "AwayTeamScore": 1
  },
  {
    "DateUtc": "01/04/23",
    "HomeTeam": "Cremonese",
    "AwayTeam": "Atalanta",
    "HomeTeamScore": 1,
    "AwayTeamScore": 3
  },
  {
    "DateUtc": "01/04/23",
    "HomeTeam": "Inter",
    "AwayTeam": "Fiorentina",
    "HomeTeamScore": 0,
    "AwayTeamScore": 1
  },
  {
    "DateUtc": "01/04/23",
    "HomeTeam": "Juventus",
    "AwayTeam": "Verona",
    "HomeTeamScore": 1,
    "AwayTeamScore": 0
  },
  {
    "DateUtc": "02/04/23",
    "HomeTeam": "Bologna",
    "AwayTeam": "Udinese",
    "HomeTeamScore": 3,
    "AwayTeamScore": 0
  },
  {
    "DateUtc": "02/04/23",
    "HomeTeam": "Monza",
    "AwayTeam": "Lazio",
    "HomeTeamScore": 0,
    "AwayTeamScore": 2
  },
  {
    "DateUtc": "02/04/23",
    "HomeTeam": "Spezia",
    "AwayTeam": "Salernitana",
    "HomeTeamScore": 1,
    "AwayTeamScore": 1
  },
  {
    "DateUtc": "02/04/23",
    "HomeTeam": "Roma",
    "AwayTeam": "Sampdoria",
    "HomeTeamScore": 3,
    "AwayTeamScore": 0
  },
  {
    "DateUtc": "02/04/23",
    "HomeTeam": "Napoli",
    "AwayTeam": "Milan",
    "HomeTeamScore": 0,
    "AwayTeamScore": 4
  },
  {
    "DateUtc": "03/04/23",
    "HomeTeam": "Empoli",
    "AwayTeam": "Lecce",
    "HomeTeamScore": 1,
    "AwayTeamScore": 0
  },
  {
    "DateUtc": "03/04/23",
    "HomeTeam": "Sassuolo",
    "AwayTeam": "Torino",
    "HomeTeamScore": 1,
    "AwayTeamScore": 1
  },
  {
    "DateUtc": "07/04/23",
    "HomeTeam": "Salernitana",
    "AwayTeam": "Inter",
    "HomeTeamScore": 1,
    "AwayTeamScore": 1
  },
  {
    "DateUtc": "07/04/23",
    "HomeTeam": "Lecce",
    "AwayTeam": "Napoli",
    "HomeTeamScore": 1,
    "AwayTeamScore": 2
  },
  {
    "DateUtc": "07/04/23",
    "HomeTeam": "Milan",
    "AwayTeam": "Empoli",
    "HomeTeamScore": 0,
    "AwayTeamScore": 0
  },
  {
    "DateUtc": "08/04/23",
    "HomeTeam": "Udinese",
    "AwayTeam": "Monza",
    "HomeTeamScore": 2,
    "AwayTeamScore": 2
  },
  {
    "DateUtc": "08/04/23",
    "HomeTeam": "Fiorentina",
    "AwayTeam": "Spezia",
    "HomeTeamScore": 1,
    "AwayTeamScore": 1
  },
  {
    "DateUtc": "08/04/23",
    "HomeTeam": "Atalanta",
    "AwayTeam": "Bologna",
    "HomeTeamScore": 0,
    "AwayTeamScore": 2
  },
  {
    "DateUtc": "08/04/23",
    "HomeTeam": "Sampdoria",
    "AwayTeam": "Cremonese",
    "HomeTeamScore": 2,
    "AwayTeamScore": 3
  },
  {
    "DateUtc": "08/04/23",
    "HomeTeam": "Torino",
    "AwayTeam": "Roma",
    "HomeTeamScore": 0,
    "AwayTeamScore": 1
  },
  {
    "DateUtc": "08/04/23",
    "HomeTeam": "Verona",
    "AwayTeam": "Sassuolo",
    "HomeTeamScore": 2,
    "AwayTeamScore": 1
  },
  {
    "DateUtc": "08/04/23",
    "HomeTeam": "Lazio",
    "AwayTeam": "Juventus",
    "HomeTeamScore": 2,
    "AwayTeamScore": 1
  },
  {
    "DateUtc": "14/04/23",
    "HomeTeam": "Cremonese",
    "AwayTeam": "Empoli",
    "HomeTeamScore": 1,
    "AwayTeamScore": 0
  },
  {
    "DateUtc": "14/04/23",
    "HomeTeam": "Spezia",
    "AwayTeam": "Lazio",
    "HomeTeamScore": 0,
    "AwayTeamScore": 3
  },
  {
    "DateUtc": "15/04/23",
    "HomeTeam": "Bologna",
    "AwayTeam": "Milan",
    "HomeTeamScore": 1,
    "AwayTeamScore": 1
  },
  {
    "DateUtc": "15/04/23",
    "HomeTeam": "Napoli",
    "AwayTeam": "Verona",
    "HomeTeamScore": 0,
    "AwayTeamScore": 0
  },
  {
    "DateUtc": "15/04/23",
    "HomeTeam": "Inter",
    "AwayTeam": "Monza",
    "HomeTeamScore": 0,
    "AwayTeamScore": 1
  },
  {
    "DateUtc": "16/04/23",
    "HomeTeam": "Lecce",
    "AwayTeam": "Sampdoria",
    "HomeTeamScore": 1,
    "AwayTeamScore": 1
  },
  {
    "DateUtc": "16/04/23",
    "HomeTeam": "Torino",
    "AwayTeam": "Salernitana",
    "HomeTeamScore": 1,
    "AwayTeamScore": 1
  },
  {
    "DateUtc": "16/04/23",
    "HomeTeam": "Sassuolo",
    "AwayTeam": "Juventus",
    "HomeTeamScore": 1,
    "AwayTeamScore": 0
  },
  {
    "DateUtc": "16/04/23",
    "HomeTeam": "Roma",
    "AwayTeam": "Udinese",
    "HomeTeamScore": 3,
    "AwayTeamScore": 0
  },
  {
    "DateUtc": "17/04/23",
    "HomeTeam": "Fiorentina",
    "AwayTeam": "Atalanta",
    "HomeTeamScore": 1,
    "AwayTeamScore": 1
  },
  {
    "DateUtc": "21/04/23",
    "HomeTeam": "Verona",
    "AwayTeam": "Bologna",
    "HomeTeamScore": 2,
    "AwayTeamScore": 1
  },
  {
    "DateUtc": "22/04/23",
    "HomeTeam": "Salernitana",
    "AwayTeam": "Sassuolo",
    "HomeTeamScore": 3,
    "AwayTeamScore": 0
  },
  {
    "DateUtc": "22/04/23",
    "HomeTeam": "Lazio",
    "AwayTeam": "Torino",
    "HomeTeamScore": 0,
    "AwayTeamScore": 1
  },
  {
    "DateUtc": "22/04/23",
    "HomeTeam": "Sampdoria",
    "AwayTeam": "Spezia",
    "HomeTeamScore": 1,
    "AwayTeamScore": 1
  },
  {
    "DateUtc": "23/04/23",
    "HomeTeam": "Empoli",
    "AwayTeam": "Inter",
    "HomeTeamScore": 0,
    "AwayTeamScore": 3
  },
  {
    "DateUtc": "23/04/23",
    "HomeTeam": "Monza",
    "AwayTeam": "Fiorentina",
    "HomeTeamScore": 3,
    "AwayTeamScore": 2
  },
  {
    "DateUtc": "23/04/23",
    "HomeTeam": "Udinese",
    "AwayTeam": "Cremonese",
    "HomeTeamScore": 3,
    "AwayTeamScore": 0
  },
  {
    "DateUtc": "23/04/23",
    "HomeTeam": "Milan",
    "AwayTeam": "Lecce",
    "HomeTeamScore": 2,
    "AwayTeamScore": 0
  },
  {
    "DateUtc": "23/04/23",
    "HomeTeam": "Juventus",
    "AwayTeam": "Napoli",
    "HomeTeamScore": 0,
    "AwayTeamScore": 1
  },
  {
    "DateUtc": "24/04/23",
    "HomeTeam": "Atalanta",
    "AwayTeam": "Roma",
    "HomeTeamScore": 3,
    "AwayTeamScore": 1
  },
  {
    "DateUtc": "28/04/23",
    "HomeTeam": "Lecce",
    "AwayTeam": "Udinese",
    "HomeTeamScore": 1,
    "AwayTeamScore": 0
  },
  {
    "DateUtc": "28/04/23",
    "HomeTeam": "Spezia",
    "AwayTeam": "Monza",
    "HomeTeamScore": 0,
    "AwayTeamScore": 2
  },
  {
    "DateUtc": "29/04/23",
    "HomeTeam": "Roma",
    "AwayTeam": "Milan",
    "HomeTeamScore": 1,
    "AwayTeamScore": 1
  },
  {
    "DateUtc": "29/04/23",
    "HomeTeam": "Torino",
    "AwayTeam": "Atalanta",
    "HomeTeamScore": 1,
    "AwayTeamScore": 2
  },
  {
    "DateUtc": "30/04/23",
    "HomeTeam": "Inter",
    "AwayTeam": "Lazio",
    "HomeTeamScore": 3,
    "AwayTeamScore": 1
  },
  {
    "DateUtc": "30/04/23",
    "HomeTeam": "Cremonese",
    "AwayTeam": "Verona",
    "HomeTeamScore": 1,
    "AwayTeamScore": 1
  },
  {
    "DateUtc": "30/04/23",
    "HomeTeam": "Napoli",
    "AwayTeam": "Salernitana",
    "HomeTeamScore": 1,
    "AwayTeamScore": 1
  },
  {
    "DateUtc": "30/04/23",
    "HomeTeam": "Sassuolo",
    "AwayTeam": "Empoli",
    "HomeTeamScore": 2,
    "AwayTeamScore": 1
  },
  {
    "DateUtc": "30/04/23",
    "HomeTeam": "Fiorentina",
    "AwayTeam": "Sampdoria",
    "HomeTeamScore": 5,
    "AwayTeamScore": 0
  },
  {
    "DateUtc": "30/04/23",
    "HomeTeam": "Bologna",
    "AwayTeam": "Juventus",
    "HomeTeamScore": 1,
    "AwayTeamScore": 1
  },
  {
    "DateUtc": "03/05/23",
    "HomeTeam": "Atalanta",
    "AwayTeam": "Spezia",
    "HomeTeamScore": 3,
    "AwayTeamScore": 2
  },
  {
    "DateUtc": "03/05/23",
    "HomeTeam": "Juventus",
    "AwayTeam": "Lecce",
    "HomeTeamScore": 2,
    "AwayTeamScore": 1
  },
  {
    "DateUtc": "03/05/23",
    "HomeTeam": "Salernitana",
    "AwayTeam": "Fiorentina",
    "HomeTeamScore": 3,
    "AwayTeamScore": 3
  },
  {
    "DateUtc": "03/05/23",
    "HomeTeam": "Sampdoria",
    "AwayTeam": "Torino",
    "HomeTeamScore": 0,
    "AwayTeamScore": 2
  },
  {
    "DateUtc": "03/05/23",
    "HomeTeam": "Lazio",
    "AwayTeam": "Sassuolo",
    "HomeTeamScore": 2,
    "AwayTeamScore": 0
  },
  {
    "DateUtc": "03/05/23",
    "HomeTeam": "Milan",
    "AwayTeam": "Cremonese",
    "HomeTeamScore": 1,
    "AwayTeamScore": 1
  },
  {
    "DateUtc": "03/05/23",
    "HomeTeam": "Monza",
    "AwayTeam": "Roma",
    "HomeTeamScore": 1,
    "AwayTeamScore": 1
  },
  {
    "DateUtc": "03/05/23",
    "HomeTeam": "Verona",
    "AwayTeam": "Inter",
    "HomeTeamScore": 0,
    "AwayTeamScore": 6
  },
  {
    "DateUtc": "04/05/23",
    "HomeTeam": "Empoli",
    "AwayTeam": "Bologna",
    "HomeTeamScore": 3,
    "AwayTeamScore": 1
  },
  {
    "DateUtc": "04/05/23",
    "HomeTeam": "Udinese",
    "AwayTeam": "Napoli",
    "HomeTeamScore": 1,
    "AwayTeamScore": 1
  },
  {
    "DateUtc": "06/05/23",
    "HomeTeam": "Milan",
    "AwayTeam": "Lazio",
    "HomeTeamScore": 2,
    "AwayTeamScore": 0
  },
  {
    "DateUtc": "06/05/23",
    "HomeTeam": "Roma",
    "AwayTeam": "Inter",
    "HomeTeamScore": 0,
    "AwayTeamScore": 2
  },
  {
    "DateUtc": "06/05/23",
    "HomeTeam": "Cremonese",
    "AwayTeam": "Spezia",
    "HomeTeamScore": 2,
    "AwayTeamScore": 0
  },
  {
    "DateUtc": "07/05/23",
    "HomeTeam": "Atalanta",
    "AwayTeam": "Juventus",
    "HomeTeamScore": 0,
    "AwayTeamScore": 2
  },
  {
    "DateUtc": "07/05/23",
    "HomeTeam": "Torino",
    "AwayTeam": "Monza",
    "HomeTeamScore": 1,
    "AwayTeamScore": 1
  },
  {
    "DateUtc": "07/05/23",
    "HomeTeam": "Napoli",
    "AwayTeam": "Fiorentina",
    "HomeTeamScore": 1,
    "AwayTeamScore": 0
  },
  {
    "DateUtc": "07/05/23",
    "HomeTeam": "Lecce",
    "AwayTeam": "Verona",
    "HomeTeamScore": 0,
    "AwayTeamScore": 1
  },
  {
    "DateUtc": "08/05/23",
    "HomeTeam": "Empoli",
    "AwayTeam": "Salernitana",
    "HomeTeamScore": 2,
    "AwayTeamScore": 1
  },
  {
    "DateUtc": "08/05/23",
    "HomeTeam": "Udinese",
    "AwayTeam": "Sampdoria",
    "HomeTeamScore": 2,
    "AwayTeamScore": 0
  },
  {
    "DateUtc": "08/05/23",
    "HomeTeam": "Sassuolo",
    "AwayTeam": "Bologna",
    "HomeTeamScore": 1,
    "AwayTeamScore": 1
  },
  {
    "DateUtc": "12/05/23",
    "HomeTeam": "Lazio",
    "AwayTeam": "Lecce",
    "HomeTeamScore": 2,
    "AwayTeamScore": 2
  },
  {
    "DateUtc": "13/05/23",
    "HomeTeam": "Salernitana",
    "AwayTeam": "Atalanta",
    "HomeTeamScore": 1,
    "AwayTeamScore": 0
  },
  {
    "DateUtc": "13/05/23",
    "HomeTeam": "Spezia",
    "AwayTeam": "Milan",
    "HomeTeamScore": 2,
    "AwayTeamScore": 0
  },
  {
    "DateUtc": "13/05/23",
    "HomeTeam": "Inter",
    "AwayTeam": "Sassuolo",
    "HomeTeamScore": 4,
    "AwayTeamScore": 2
  },
  {
    "DateUtc": "14/05/23",
    "HomeTeam": "Verona",
    "AwayTeam": "Torino",
    "HomeTeamScore": 0,
    "AwayTeamScore": 1
  },
  {
    "DateUtc": "14/05/23",
    "HomeTeam": "Fiorentina",
    "AwayTeam": "Udinese",
    "HomeTeamScore": 2,
    "AwayTeamScore": 0
  },
  {
    "DateUtc": "14/05/23",
    "HomeTeam": "Monza",
    "AwayTeam": "Napoli",
    "HomeTeamScore": 2,
    "AwayTeamScore": 0
  },
  {
    "DateUtc": "14/05/23",
    "HomeTeam": "Bologna",
    "AwayTeam": "Roma",
    "HomeTeamScore": 0,
    "AwayTeamScore": 0
  },
  {
    "DateUtc": "14/05/23",
    "HomeTeam": "Juventus",
    "AwayTeam": "Cremonese",
    "HomeTeamScore": 2,
    "AwayTeamScore": 0
  },
  {
    "DateUtc": "15/05/23",
    "HomeTeam": "Sampdoria",
    "AwayTeam": "Empoli",
    "HomeTeamScore": 1,
    "AwayTeamScore": 1
  },
  {
    "DateUtc": "19/05/23",
    "HomeTeam": "Sassuolo",
    "AwayTeam": "Monza",
    "HomeTeamScore": 1,
    "AwayTeamScore": 2
  },
  {
    "DateUtc": "20/05/23",
    "HomeTeam": "Cremonese",
    "AwayTeam": "Bologna",
    "HomeTeamScore": 1,
    "AwayTeamScore": 5
  },
  {
    "DateUtc": "20/05/23",
    "HomeTeam": "Atalanta",
    "AwayTeam": "Verona",
    "HomeTeamScore": 3,
    "AwayTeamScore": 1
  },
  {
    "DateUtc": "20/05/23",
    "HomeTeam": "Milan",
    "AwayTeam": "Sampdoria",
    "HomeTeamScore": 5,
    "AwayTeamScore": 1
  },
  {
    "DateUtc": "21/05/23",
    "HomeTeam": "Lecce",
    "AwayTeam": "Spezia",
    "HomeTeamScore": 0,
    "AwayTeamScore": 0
  },
  {
    "DateUtc": "21/05/23",
    "HomeTeam": "Torino",
    "AwayTeam": "Fiorentina",
    "HomeTeamScore": 1,
    "AwayTeamScore": 1
  },
  {
    "DateUtc": "21/05/23",
    "HomeTeam": "Napoli",
    "AwayTeam": "Inter",
    "HomeTeamScore": 3,
    "AwayTeamScore": 1
  },
  {
    "DateUtc": "21/05/23",
    "HomeTeam": "Udinese",
    "AwayTeam": "Lazio",
    "HomeTeamScore": 0,
    "AwayTeamScore": 1
  },
  {
    "DateUtc": "22/05/23",
    "HomeTeam": "Roma",
    "AwayTeam": "Salernitana",
    "HomeTeamScore": 2,
    "AwayTeamScore": 2
  },
  {
    "DateUtc": "22/05/23",
    "HomeTeam": "Empoli",
    "AwayTeam": "Juventus",
    "HomeTeamScore": 4,
    "AwayTeamScore": 1
  },
  {
    "DateUtc": "26/05/23",
    "HomeTeam": "Sampdoria",
    "AwayTeam": "Sassuolo",
    "HomeTeamScore": 2,
    "AwayTeamScore": 2
  },
  {
    "DateUtc": "27/05/23",
    "HomeTeam": "Salernitana",
    "AwayTeam": "Udinese",
    "HomeTeamScore": 3,
    "AwayTeamScore": 2
  },
  {
    "DateUtc": "27/05/23",
    "HomeTeam": "Spezia",
    "AwayTeam": "Torino",
    "HomeTeamScore": 0,
    "AwayTeamScore": 4
  },
  {
    "DateUtc": "27/05/23",
    "HomeTeam": "Fiorentina",
    "AwayTeam": "Roma",
    "HomeTeamScore": 2,
    "AwayTeamScore": 1
  },
  {
    "DateUtc": "27/05/23",
    "HomeTeam": "Inter",
    "AwayTeam": "Atalanta",
    "HomeTeamScore": 3,
    "AwayTeamScore": 2
  },
  {
    "DateUtc": "28/05/23",
    "HomeTeam": "Verona",
    "AwayTeam": "Empoli",
    "HomeTeamScore": 1,
    "AwayTeamScore": 1
  },
  {
    "DateUtc": "28/05/23",
    "HomeTeam": "Bologna",
    "AwayTeam": "Napoli",
    "HomeTeamScore": 2,
    "AwayTeamScore": 2
  },
  {
    "DateUtc": "28/05/23",
    "HomeTeam": "Monza",
    "AwayTeam": "Lecce",
    "HomeTeamScore": 0,
    "AwayTeamScore": 1
  },
  {
    "DateUtc": "28/05/23",
    "HomeTeam": "Lazio",
    "AwayTeam": "Cremonese",
    "HomeTeamScore": 3,
    "AwayTeamScore": 2
  },
  {
    "DateUtc": "28/05/23",
    "HomeTeam": "Juventus",
    "AwayTeam": "Milan",
    "HomeTeamScore": 0,
    "AwayTeamScore": 1
  },
  {
    "DateUtc": "02/06/23",
    "HomeTeam": "Sassuolo",
    "AwayTeam": "Fiorentina",
    "HomeTeamScore": 1,
    "AwayTeamScore": 3
  },
  {
    "DateUtc": "03/06/23",
    "HomeTeam": "Torino",
    "AwayTeam": "Inter",
    "HomeTeamScore": 0,
    "AwayTeamScore": 1
  },
  {
    "DateUtc": "03/06/23",
    "HomeTeam": "Cremonese",
    "AwayTeam": "Salernitana",
    "HomeTeamScore": 2,
    "AwayTeamScore": 0
  },
  {
    "DateUtc": "03/06/23",
    "HomeTeam": "Empoli",
    "AwayTeam": "Lazio",
    "HomeTeamScore": 0,
    "AwayTeamScore": 2
  },
  {
    "DateUtc": "04/06/23",
    "HomeTeam": "Napoli",
    "AwayTeam": "Sampdoria",
    "HomeTeamScore": 2,
    "AwayTeamScore": 0
  },
  {
    "DateUtc": "04/06/23",
    "HomeTeam": "Atalanta",
    "AwayTeam": "Monza",
    "HomeTeamScore": 5,
    "AwayTeamScore": 2
  },
  {
    "DateUtc": "04/06/23",
    "HomeTeam": "Lecce",
    "AwayTeam": "Bologna",
    "HomeTeamScore": 2,
    "AwayTeamScore": 3
  },
  {
    "DateUtc": "04/06/23",
    "HomeTeam": "Milan",
    "AwayTeam": "Verona",
    "HomeTeamScore": 3,
    "AwayTeamScore": 1
  },
  {
    "DateUtc": "04/06/23",
    "HomeTeam": "Roma",
    "AwayTeam": "Spezia",
    "HomeTeamScore": 2,
    "AwayTeamScore": 1
  },
  {
    "DateUtc": "04/06/23",
    "HomeTeam": "Udinese",
    "AwayTeam": "Juventus",
    "HomeTeamScore": 0,
    "AwayTeamScore": 1
  }
]